{}{"quantity":1,"price":35,"name":"Brown Cowboy"},{}{"quantity":1,"price":35,"name":"Brown Cowboy"},{}{"quantity":1,"price":35,"name":"Brown Cowboy"},{}{"quantity":1,"price":35,"name":"Brown Cowboy"},{}{"quantity":1,"price":35,"name":"Brown Cowboy"},{}{"quantity":1,"price":35,"name":"Brown Cowboy"},{}{"quantity":1,"price":35,"name":"Brown Cowboy"},{}{"quantity":1,"price":35,"name":"Brown Cowboy"},{}{"quantity":1,"price":35,"name":"Brown Cowboy"},{}{"quantity":1,"price":35,"name":"Brown Cowboy"},{"Amount":3500,"Name":"abdullah abu-alhaijja","City":"goteborg","Country":"Sweden","Address":"Hellstedtsgatan 7","Postnumber":"41456","Brand":"Visa","Source_Country":"Sweden"}{},{}{"quantity":1,"price":35,"name":"Brown Cowboy"},{}{"quantity":1,"price":18,"name":"Blue Beanie"},{}{"quantity":2,"price":18,"name":"Blue Beanie"},{}{"quantity":1,"price":25,"name":"Blue Warm"},{}{"quantity":1,"price":18,"name":"Blue Beanie"},{}{"quantity":1,"price":18,"name":"Blue Beanie"},{"Amount":1800,"Name":"Ali Ezadkhaha","City":"Partille","Country":"Sweden","Address":"Postgången 1 A","Postnumber":"43334","Brand":"Visa","Source_Country":"Sweden"}{},{}{"quantity":1,"price":18,"name":"Blue Beanie"},{"Amount":1800,"Name":"Ali Ezadkhaha","City":"Partille","Country":"Sweden","Address":"Postgången 1 A","Postnumber":"43334","Brand":"Visa","Source_Country":"Sweden"}{},{}{"quantity":1,"price":18,"name":"Blue Beanie"},{}{"quantity":3,"price":18,"name":"Blue Beanie"},{}{"quantity":1,"price":18,"name":"Blue Beanie"},{}{"quantity":1,"price":18,"name":"Blue Beanie"},{}{"quantity":1,"price":18,"name":"Blue Beanie"},{}{"quantity":2,"price":18,"name":"Blue Beanie"},{}{"quantity":1,"price":18,"name":"Blue Beanie"},{}{"quantity":1,"price":18,"name":"Blue Beanie"},{}{"quantity":1,"price":18,"name":"Blue Beanie"},{}{"quantity":1,"price":18,"name":"Blue Beanie"},{}{"quantity":1,"price":18,"name":"Blue Beanie"},{}{"quantity":1,"price":18,"name":"Blue Beanie"},{}{"quantity":1,"price":18,"name":"Blue Beanie"},{}{"quantity":1,"price":18,"name":"Blue Beanie"},{}{"quantity":1,"price":18,"name":"Blue Beanie"},{}{"quantity":2,"price":18,"name":"Blue Beanie"},{}{"quantity":1,"price":18,"name":"Blue Beanie"},{}{"quantity":1,"price":18,"name":"Blue Beanie"},{"Amount":1800,"Name":"Ali Ezadkhaha","City":"Partille","Country":"Sweden","Address":"Postgången 1 A","Postnumber":"43334","Brand":"Visa","Source_Country":"Sweden"}{},{}{"quantity":1,"price":18,"name":"Blue Beanie"},{"Amount":1800,"Name":"jjkjk","City":"hhh","Country":"Sweden","Address":"jjj","Postnumber":"6666","Brand":"Visa","Source_Country":"Sweden"}{},{}{"quantity":1,"price":18,"name":"Blue Beanie"},{"Amount":1800,"Name":"Ali Ezadkhaha","City":"Partille","Country":"Sweden","Address":"Postgången 1 A","Postnumber":"43334","Brand":"Visa","Source_Country":"Sweden"}{},{}{"quantity":1,"price":18,"name":"Blue Beanie"},{"Amount":1800,"Name":"Ali Ezadkhaha","City":"Partille","Country":"Sweden","Address":"Postgången 1 A","Postnumber":"43334","Brand":"Visa","Source_Country":"Sweden"}{},{}{"quantity":1,"price":18,"name":"Blue Beanie"},{}{"quantity":2,"price":18,"name":"Blue Beanie"},{"Amount":3600,"Name":"Ali Ezadkhaha","City":"Partille","Country":"Sweden","Address":"Postgången 1 A","Postnumber":"43334","Brand":"Visa","Source_Country":"Sweden"}{},{}{"quantity":1,"price":18,"name":"Blue Beanie"},{"Amount":1800,"Name":"Ali Ezadkhaha","City":"Partille","Country":"Sweden","Address":"Postgången 1 A","Postnumber":"43334","Brand":"Visa","Source_Country":"Sweden"}{},{}{"quantity":1,"price":18,"name":"Blue Beanie"},{"Amount":1800,"Name":"Ali Ezadkhaha","City":"Partille","Country":"Sweden","Address":"Postgången 1 A","Postnumber":"43334","Brand":"Visa","Source_Country":"Sweden"}{},{}{"quantity":2,"price":18,"name":"Blue Beanie"},{}{"quantity":2,"price":18,"name":"Blue Beanie"},{"Amount":3600,"Name":"Ali Ezadkhaha","City":"Partille","Country":"Sweden","Address":"Postgången 1 A","Postnumber":"43334","Brand":"Visa","Source_Country":"Sweden"}{},{}{"quantity":2,"price":18,"name":"Blue Beanie"},{}{"quantity":2,"price":18,"name":"Blue Beanie"},{"Amount":3600,"Name":"Ali Ezadkhaha","City":"Partille","Country":"Sweden","Address":"Postgången 1 A","Postnumber":"43334","Brand":"Visa","Source_Country":"Sweden"}{},{}{"quantity":4,"price":18,"name":"Blue Beanie"},{}{"quantity":1,"price":18,"name":"Blue Beanie"},{"Amount":1800,"Name":"Ali Ezadkhaha","City":"Partille","Country":"Sweden","Address":"Postgången 1 A","Postnumber":"43334","Brand":"Visa","Source_Country":"Sweden"}{},{}{"quantity":1,"price":18,"name":"Blue Beanie"},{}{"quantity":1,"price":18,"name":"Blue Beanie"},{}{"quantity":2,"price":18,"name":"Blue Beanie"},{"Amount":3600,"Name":"Ali Ezadkhaha","City":"Partille","Country":"Sweden","Address":"Postgången 1 A","Postnumber":"43334","Brand":"Visa","Source_Country":"Sweden"}{},{}{"quantity":1,"price":18,"name":"Blue Beanie"},{"Amount":1800,"Name":"Ali Ezadkhaha","City":"Partille","Country":"Sweden","Address":"Postgången 1 A","Postnumber":"43334","Brand":"Visa","Source_Country":"Sweden"}{},{}{"quantity":2,"price":18,"name":"Blue Beanie"},{}{"quantity":2,"price":18,"name":"Blue Beanie"},{}{"quantity":1,"price":25,"name":"Blue Warm"},{"Amount":6100,"Name":"Ali Ezadkhaha","City":"Partille","Country":"Sweden","Address":"Postgången 1 A","Postnumber":"43334","Brand":"Visa","Source_Country":"Sweden"}{},{}{"quantity":2,"price":18,"name":"Blue Beanie"},{}{"quantity":1,"price":25,"name":"Blue Warm"},{}{"quantity":2,"price":18,"name":"Blue Beanie"},{}{"quantity":1,"price":25,"name":"Blue Warm"},{"Amount":6100,"Name":"Ali Ezadkhaha","City":"Partille","Country":"Sweden","Address":"Postgången 1 A","Postnumber":"43334","Brand":"Visa","Source_Country":"Sweden"}{},{}{"quantity":2,"price":18,"name":"Blue Beanie"},{}{"quantity":1,"price":25,"name":"Blue Warm"},{"Amount":6100,"Name":"Ali Ezadkhaha","City":"Partille","Country":"Sweden","Address":"Postgången 1 A","Postnumber":"43334","Brand":"Visa","Source_Country":"Sweden"}{},{}{"quantity":2,"price":18,"name":"Blue Beanie"},{}{"quantity":1,"price":25,"name":"Blue Warm"},{}{"quantity":2,"price":18,"name":"Blue Beanie"},{}{"quantity":1,"price":25,"name":"Blue Warm"},{"Amount":6100,"Name":"Ali Ezadkhaha","City":"Partille","Country":"Sweden","Address":"Postgången 1 A","Postnumber":"43334","Brand":"Visa","Source_Country":"Sweden"}{},{}{"quantity":2,"price":25,"name":"Blue Warm"},{"Amount":8600,"Name":"Ali Ezadkhaha","City":"Partille","Country":"Sweden","Address":"Postgången 1 A","Postnumber":"43334","Brand":"Visa","Source_Country":"Sweden"}{},{}{"quantity":2,"price":18,"name":"Blue Beanie"},{}{"quantity":2,"price":25,"name":"Blue Warm"},{}{"quantity":1,"price":18,"name":"Blue Beanie"},{"Amount":1800,"Name":"Ali Ezadkhaha","City":"Partille","Country":"Sweden","Address":"Postgången 1 A","Postnumber":"43334","Brand":"Visa","Source_Country":"Sweden"}{},{}{"quantity":1,"price":18,"name":"Blue Beanie"},{"Amount":1800,"Name":"Ali Ezadkhaha","City":"Partille","Country":"Sweden","Address":"Postgången 1 A","Postnumber":"43334","Brand":"Visa","Source_Country":"Sweden"}{},{}{"quantity":1,"price":18,"name":"Blue Beanie"},{"Amount":1800,"Name":"Ali Ezadkhaha","City":"Partille","Country":"Sweden","Address":"Postgången 1 A","Postnumber":"43334","Brand":"Visa","Source_Country":"Sweden"}{},{}{"quantity":1,"price":18,"name":"Blue Beanie"},{}{"quantity":1,"price":18,"name":"Blue Beanie"},{"Amount":1800,"Name":"Ali Ezadkhaha","City":"Partille","Country":"Sweden","Address":"Postgången 1 A","Postnumber":"43334","Brand":"Visa","Source_Country":"Sweden"}{},{}{"quantity":1,"price":18,"name":"Blue Beanie"},{"Amount":1800,"Name":"Ali Ezadkhaha","City":"Partille","Country":"Sweden","Address":"Postgången 1 A","Postnumber":"43334","Brand":"Visa","Source_Country":"Sweden"}{},{}{"quantity":1,"price":18,"name":"Blue Beanie"},{}{"quantity":1,"price":18,"name":"Blue Beanie"},{"Amount":1800,"Name":"Ali Ezadkhaha","City":"Partille","Country":"Sweden","Address":"Postgången 1 A","Postnumber":"43334","Brand":"Visa","Source_Country":"Sweden"}{},{}{"quantity":1,"price":18,"name":"Blue Beanie"},{}{"quantity":1,"price":18,"name":"Blue Beanie"},{}{"quantity":1,"price":18,"name":"Blue Beanie"},{}{"quantity":1,"price":18,"name":"Blue Beanie"},{"Amount":1800,"Name":"Ali Ezadkhaha","City":"Partille","Country":"Sweden","Address":"Postgången 1 A","Postnumber":"43334","Brand":"Visa","Source_Country":"Sweden"}{},{}{"quantity":1,"price":18,"name":"Blue Beanie"},{"Amount":1800,"Name":"Ali Ezadkhaha","City":"Partille","Country":"Sweden","Address":"Postgången 1 A","Postnumber":"43334","Brand":"Visa","Source_Country":"Sweden"}{},{}{"quantity":1,"price":18,"name":"Blue Beanie"},{}{"quantity":1,"price":18,"name":"Blue Beanie"},{"Amount":1800,"Name":"Ali Ezadkhaha","City":"Partille","Country":"Sweden","Address":"Postgången 1 A","Postnumber":"43334","Brand":"Visa","Source_Country":"Sweden"}{},{}{"quantity":1,"price":18,"name":"Blue Beanie"},{"Amount":1800,"Name":"Ali Ezadkhaha","City":"Partille","Country":"Sweden","Address":"Postgången 1 A","Postnumber":"43334","Brand":"Visa","Source_Country":"Sweden"}{},{}{"quantity":1,"price":25,"name":"Blue Warm"},